dataall_core/__init__.py
dataall_core/auth/__init__.py
dataall_core/auth/auth.py
dataall_core/auth/cognito_auth.py
dataall_core/auth/custom_auth.py
dataall_core/base_client.py
dataall_core/dataall_client.py
dataall_core/exceptions.py
dataall_core/loader.py
dataall_core/profile.py
dataall_core/schema/v2_5.json
dataall_core/schema/v2_6.json
dataall_core/schema/v2_6_1.json
dataall_core/schema/v2_7_0.json
dataall_core/schema/v2_8_0.json
dataall_core/schema/v2_9_0.json
dataall_core-0.4.3.dist-info/METADATA
dataall_core-0.4.3.dist-info/WHEEL
dataall_core-0.4.3.dist-info/licenses/LICENSE
dataall_core-0.4.3.dist-info/licenses/NOTICE
dataall_core-0.4.3.dist-info/RECORD
